{
    "protocol": "ftp",
    "port": 21,
    "username": "staging_voltas@voltas.twostaging.com",
    "password": "IGHrsx15Ow;j",
    "remotePath": "/",
    "ignore": [ "/_vds-src/", 
                "/.vscode/", 
                "/node_modules/", 
                "/.gitignore", 
                "/VoltasEE_DEV.code-workspace", 
                "/backup.zip",
                "/gulpfile.js", 
                "/package.json",
                "/package-lock.json",
                "/SPECS"],
    "watcher": {
        "files": "{EE_system/user/templates/voltas/*/**,public_html/themes/user/site/default/asset/css/*,public_html/themes/user/site/default/asset/js/*}",
        "autoUpload": true,
        "autoDelete": false
    },
    "profiles": {
        "dev": { 
        "host": "twostaging.com",
        "remotePath": "/",
        "uploadOnSave": true
        },
        "prod": {
        "host": "prod-host",
        "remotePath": "/",
        "uploadOnSave": false
        }
    },
    "defaultProfile": "dev"
}